mf_adapter/VERSION
mf_adapter/__init__.py
mf_adapter/_pymf_transfer.cpython-311-aarch64-linux-gnu.so
mf_adapter/lib/libmf_hybm_core.so
mf_adapter/lib/libmf_smem.so
mf_adapter.libs/libmf_hybm_core-4a4dca26.so
mf_adapter.libs/libmf_smem-0b161aff.so
mf_adapter-1.0.0.dist-info/METADATA
mf_adapter-1.0.0.dist-info/WHEEL
mf_adapter-1.0.0.dist-info/top_level.txt
mf_adapter-1.0.0.dist-info/RECORD
