Metadata-Version: 2.4
Name: mf_adapter
Version: 1.0.0
Summary: python api for mf_adapter
Home-page: https://gitee.com/ascend/memfabric_hybrid
Author: 
Author-email: 
License: Apache License Version 2.0
Keywords: KVCache,PD transfer
Requires-Python: >=3.7
Dynamic: home-page
Dynamic: keywords
Dynamic: license
Dynamic: requires-python
Dynamic: summary
